pykeesap/__init__.py
pykeesap/__main__.py
pykeesap/commands.py
pykeesap/keepass_base.py
pykeesap/keepass_entry.py
pykeesap/password_manager.py
PyKeeSAP-1.0.2.dist-info/LICENSE
PyKeeSAP-1.0.2.dist-info/METADATA
PyKeeSAP-1.0.2.dist-info/WHEEL
PyKeeSAP-1.0.2.dist-info/entry_points.txt
PyKeeSAP-1.0.2.dist-info/top_level.txt
PyKeeSAP-1.0.2.dist-info/RECORD
