Metadata-Version: 2.1
Name: PyKeeSAP
Version: 1.0.2
Summary: SAP password manager with KeePass
Home-page: https://github.com/gutskodv/PyKeeSAP
Author: Dmitry Gutsko
Author-email: gutskodv@gmail.com
License: GPL v2
Platform: UNKNOWN
Requires-Dist: PySapGui (>=1.0.2)
Requires-Dist: pykeepass (>=3.2.1)
